{"sets":[{"name":"Cars","terms":[{"name":"car1","properties":[{"group":"color","value":"red"},{"group":"make","value":"ford"},{"group":"model","value":"taurus"}]},{"name":"car2","properties":[{"group":"color","value":"white"},{"group":"make","value":"chevy"},{"group":"model","value":"sonic"}]},{"name":"car3","properties":[{"group":"color","value":"black"},{"group":"make","value":"volkswagon"},{"group":"model","value":"beetle"}]},{"name":"car4","properties":[{"group":"color","value":"green"},{"group":"make","value":"kia"},{"group":"model","value":"soul"}]}]},{"name":"Flowers","terms":[{"name":"Snowdrop","properties":[{"group":"genus","value":"Galanthus"},{"group":"flower color","value":"white"},{"group":"season","value":"early spring"}]},{"name":"Daylily","properties":[{"group":"genus","value":"Hemerocallis"},{"group":"flower color","value":"yellow"},{"group":"season","value":"summer"}]},{"name":"Autumn Crocus","properties":[{"group":"genus","value":"Colchicum"},{"group":"flower color","value":"pink"},{"group":"season","value":"fall"}]},{"name":"Flowering Onion","properties":[{"group":"genus","value":"Allium"},{"group":"flower color","value":"purple"},{"group":"season","value":"spring"}]}]}]}
